{
    "products": [
        {
            "id": 1,
            "name": "Food Item 1",
            "description": "Egg sandwich",
            "imageUrl": "pen1.jpg",
            "brand": "Australia Dairy Company",
            "popularity": 5,
            "cost": 5,
            "prices": [
                {
                    "tier": 0,
                    "price": "15"
                },
                {
                    "tier": 1,
                    "price": "15"
                },
                {
                    "tier": 2,
                    "price": "15"
                }
            ],
            "type": "writing_tools",
            "feature": "hot",
            "size": "small"
        },
        {
            "id": 2,
            "name": "Food Item 2",
            "description": "The most popular correction tape in Hong Kong. It is 5mm x 6mm long. ",
            "imageUrl": "correction_tape.png",
            "brand": "Australia Dairy Company",
            "popularity": 4,
            "cost": 5,
            "prices": [
                {
                    "tier": 0,
                    "price": "15"
                },
                {
                    "tier": 1,
                    "price": "15"
                },
                {
                    "tier": 2,
                    "price": "15"
                }
            ],
            "type": "writing_tools",
            "feature": "hot",
            "size": "small"
        },
        {
            "id": 3,
            "name": "Food Item 3",
            "description": "Some desert.",
            "imageUrl": "a4paper.png",
            "brand": "Australia Dairy Company",
            "popularity": 3,
            "cost": 10,
            "prices": [
                {
                    "tier": 0,
                    "price": "36"
                },
                {
                    "tier": 1,
                    "price": "36"
                },
                {
                    "tier": 2,
                    "price": "36"
                }
            ],
            "type": "paper_products",
            "feature": "",
            "size": "medium"
        }
    ],
    "reservation": [
        {
            "id": 0,
            "ticketId": "",
            "headCount": 0,
            "userId": "",
            "arrivalTime": "",
            "isActive": true,
            "createdAt": ""
        }
    ],
    "tables": [
        {
            "id":0,
            "tableNumber":1,
            "seated":false
        },
        {
            "id":1,
            "tableNumber":2,
            "seated":false
        },
        {
            "id":2,
            "tableNumber":3,
            "seated":false
        },
        {
            "id":3,
            "tableNumber":4,
            "seated":false
        }
    ],
    "orders": [
        {
          "id": 0,
          "userId": 21,
          "items": [
            {
              "productId": 25,
              "quantity": 5
            },
            {
              "productId": 18,
              "quantity": 3
            }
          ],
          "price": 0,
          "profit": 0,
          "orderCompleted": false,
          "table":1,
          "orderId":"",
          "ticketId": "",
          "parcelLocation": [
            "22.2999",
            "114.1996"
          ],
          "status": 0,
          "createdAt": "2023-07-19T19:56:44.923Z"
        }
    ]
}